omeco/__init__.py
omeco/__pycache__/__init__.cpython-311.pyc
omeco/_core.cpython-311-darwin.so
omeco-0.2.2.dist-info/METADATA
omeco-0.2.2.dist-info/WHEEL
omeco-0.2.2.dist-info/RECORD
