Metadata-Version: 2.4
Name: omeco
Version: 0.2.2
Classifier: Development Status :: 4 - Beta
Classifier: Intended Audience :: Science/Research
Classifier: License :: OSI Approved :: MIT License
Classifier: Programming Language :: Python :: 3
Classifier: Programming Language :: Python :: 3.8
Classifier: Programming Language :: Python :: 3.9
Classifier: Programming Language :: Python :: 3.10
Classifier: Programming Language :: Python :: 3.11
Classifier: Programming Language :: Python :: 3.12
Classifier: Programming Language :: Python :: 3.13
Classifier: Programming Language :: Python :: 3.14
Classifier: Programming Language :: Rust
Classifier: Topic :: Scientific/Engineering
Requires-Dist: pytest>=7.0 ; extra == 'test'
Requires-Dist: networkx>=2.6 ; extra == 'test'
Provides-Extra: test
Summary: Tensor network contraction order optimization
Keywords: tensor,einsum,optimization,contraction,quantum
License: MIT
Requires-Python: >=3.8
Project-URL: Documentation, https://docs.rs/omeco
Project-URL: Homepage, https://github.com/GiggleLiu/omeco
Project-URL: Repository, https://github.com/GiggleLiu/omeco
